MANIFEST.in
README.md
setup.py
django_autolinks/__init__.py
django_autolinks/models.py
django_autolinks/tests.py
django_autolinks/utils.py
django_autolinks/views.py
django_autolinks.egg-info/PKG-INFO
django_autolinks.egg-info/SOURCES.txt
django_autolinks.egg-info/dependency_links.txt
django_autolinks.egg-info/top_level.txt