Metadata-Version: 1.0
Name: django-autolinks
Version: 0.1.0
Summary: App for storing links and automatic link extraction from markdown texts.
Home-page: http://github.com/svetlyak40wt/django-autolinks/
Author: Alexander Artemenko
Author-email: svetlyak.40wt@gmail.com
License: New BSD License
Keywords: django apps blogging
Platform: UNKNOWN
Classifier: Development Status :: 3 - Alpha
Classifier: Environment :: Plugins
Classifier: Framework :: Django
Classifier: Intended Audience :: Developers
Classifier: License :: OSI Approved :: BSD License
Classifier: Programming Language :: Python
Classifier: Topic :: Software Development :: Libraries :: Python Modules
